odoo/addons/product_attachment_zipped_download/README.rst
odoo/addons/product_attachment_zipped_download/__init__.py
odoo/addons/product_attachment_zipped_download/__manifest__.py
odoo/addons/product_attachment_zipped_download/data/ir_actions_server_data.xml
odoo/addons/product_attachment_zipped_download/i18n/es.po
odoo/addons/product_attachment_zipped_download/i18n/it.po
odoo/addons/product_attachment_zipped_download/i18n/product_attachment_zipped_download.pot
odoo/addons/product_attachment_zipped_download/models/__init__.py
odoo/addons/product_attachment_zipped_download/models/product_product.py
odoo/addons/product_attachment_zipped_download/models/product_template.py
odoo/addons/product_attachment_zipped_download/readme/CONTRIBUTORS.md
odoo/addons/product_attachment_zipped_download/readme/DESCRIPTION.md
odoo/addons/product_attachment_zipped_download/static/description/icon.png
odoo/addons/product_attachment_zipped_download/static/description/index.html
odoo/addons/product_attachment_zipped_download/tests/__init__.py
odoo/addons/product_attachment_zipped_download/tests/test_product_attachment_zipped_download.py
odoo_addon_product_attachment_zipped_download-18.0.1.0.0.2.dist-info/METADATA
odoo_addon_product_attachment_zipped_download-18.0.1.0.0.2.dist-info/WHEEL
odoo_addon_product_attachment_zipped_download-18.0.1.0.0.2.dist-info/top_level.txt
odoo_addon_product_attachment_zipped_download-18.0.1.0.0.2.dist-info/RECORD
